mcp_server_nucleus/__init__.py
mcp_server_nucleus/__main__.py
mcp_server_nucleus/cli.py
mcp_server_nucleus/commitment_core.py
mcp_server_nucleus/commitment_ledger.py
mcp_server_nucleus/tool_tiers.py
mcp_server_nucleus/daemon/safety/lock.py
mcp_server_nucleus/runtime/__init__.py
mcp_server_nucleus/runtime/agent.py
mcp_server_nucleus/runtime/agent_pool.py
mcp_server_nucleus/runtime/auth.py
mcp_server_nucleus/runtime/autopilot.py
mcp_server_nucleus/runtime/broker.py
mcp_server_nucleus/runtime/budget.py
mcp_server_nucleus/runtime/common.py
mcp_server_nucleus/runtime/context_manager.py
mcp_server_nucleus/runtime/context_rules.json
mcp_server_nucleus/runtime/crdt_task_store.py
mcp_server_nucleus/runtime/critic.py
mcp_server_nucleus/runtime/daemon.py
mcp_server_nucleus/runtime/dashboard.py
mcp_server_nucleus/runtime/depth_ops.py
mcp_server_nucleus/runtime/event_ops.py
mcp_server_nucleus/runtime/event_stream.py
mcp_server_nucleus/runtime/export.py
mcp_server_nucleus/runtime/factory.py
mcp_server_nucleus/runtime/federation.py
mcp_server_nucleus/runtime/fetcher.py
mcp_server_nucleus/runtime/file_monitor.py
mcp_server_nucleus/runtime/firestore_bridge.py
mcp_server_nucleus/runtime/gcloud_ops.py
mcp_server_nucleus/runtime/hooks.py
mcp_server_nucleus/runtime/inspector.py
mcp_server_nucleus/runtime/installer.py
mcp_server_nucleus/runtime/ipc_auth.py
mcp_server_nucleus/runtime/lifecycle.py
mcp_server_nucleus/runtime/llm_client.py
mcp_server_nucleus/runtime/llm_tiers.json
mcp_server_nucleus/runtime/locking.py
mcp_server_nucleus/runtime/memory.py
mcp_server_nucleus/runtime/mounter.py
mcp_server_nucleus/runtime/nuke_protocol.py
mcp_server_nucleus/runtime/orchestrator.py
mcp_server_nucleus/runtime/orchestrator_unified.py
mcp_server_nucleus/runtime/orchestrator_v3.py
mcp_server_nucleus/runtime/plugin_loader.py
mcp_server_nucleus/runtime/policy.py
mcp_server_nucleus/runtime/profiling.py
mcp_server_nucleus/runtime/prometheus.py
mcp_server_nucleus/runtime/proposals.py
mcp_server_nucleus-0.6.0.dist-info/METADATA
mcp_server_nucleus-0.6.0.dist-info/WHEEL
mcp_server_nucleus-0.6.0.dist-info/entry_points.txt
mcp_server_nucleus-0.6.0.dist-info/licenses/LICENSE
mcp_server_nucleus-0.6.0.dist-info/RECORD
