Metadata-Version: 2.4
Name: mcp-server-nucleus
Version: 0.6.0
Summary: The Agent Control Plane - Default-Deny Security for MCP Servers
Author-email: Nucleus Team <hello@nucleus-mcp.com>
License-File: LICENSE
Requires-Python: >=3.10
Requires-Dist: beautifulsoup4>=4.12.0
Requires-Dist: cryptography>=41.0.0
Requires-Dist: duckduckgo-search>=4.0.0
Requires-Dist: fastmcp
Requires-Dist: google-cloud-firestore>=2.11.0
Requires-Dist: google-genai
Requires-Dist: nest-asyncio
Requires-Dist: pydantic
Requires-Dist: watchdog>=3.0.0
Provides-Extra: dev
Requires-Dist: pytest-cov; extra == 'dev'
Requires-Dist: pytest>=7.0; extra == 'dev'
Requires-Dist: ruff; extra == 'dev'
